pyopal/_align.pyi
pyopal/shared_mutex.pxd
pyopal/lib.pyi
pyopal/CMakeLists.txt
pyopal/_align.py
pyopal/__init__.pxd
pyopal/lib.cpython-312-darwin.so
pyopal/lib.pxd
pyopal/__init__.py
pyopal/opal.pxd
pyopal/lib.pyx
pyopal/py.typed
pyopal/opal.h
pyopal/platform/CMakeLists.txt
pyopal/platform/pyx.in
pyopal/platform/__init__.py
pyopal/platform/.gitignore
pyopal/platform/neon.cpython-312-darwin.so
pyopal/tests/test_result.py
pyopal/tests/test_database.py
pyopal/tests/test_aligner.py
pyopal/tests/__init__.py
pyopal/tests/test_doctest.py
pyopal/tests/test_align.py
pyopal/tests/test_alphabet.py
pyopal-0.7.3.dist-info/RECORD
pyopal-0.7.3.dist-info/WHEEL
pyopal-0.7.3.dist-info/METADATA
pyopal-0.7.3.dist-info/licenses/COPYING
