Metadata-Version: 2.2
Name: pyopal
Version: 0.7.3
Summary: Cython bindings and Python interface to Opal, a SIMD-accelerated pairwise aligner.
Keywords: bioinformatics,pairwise,sequence,alignment,opal
Author-Email: Martin Larralde <martin.larralde@embl.de>
License: MIT License
Classifier: Development Status :: 4 - Beta
Classifier: Intended Audience :: Developers
Classifier: Intended Audience :: Science/Research
Classifier: License :: OSI Approved :: MIT License
Classifier: Operating System :: OS Independent
Classifier: Programming Language :: C++
Classifier: Programming Language :: Cython
Classifier: Programming Language :: Python :: 3.7
Classifier: Programming Language :: Python :: 3.8
Classifier: Programming Language :: Python :: 3.9
Classifier: Programming Language :: Python :: 3.10
Classifier: Programming Language :: Python :: 3.11
Classifier: Programming Language :: Python :: 3.12
Classifier: Programming Language :: Python :: 3.13
Classifier: Programming Language :: Python :: Implementation :: CPython
Classifier: Programming Language :: Python :: Implementation :: PyPy
Classifier: Topic :: Scientific/Engineering :: Bio-Informatics
Classifier: Topic :: Scientific/Engineering :: Medical Science Apps.
Classifier: Typing :: Typed
Project-URL: Homepage, https://github.com/althonos/pyopal/
Project-URL: Documentation, https://pyopal.readthedocs.io/en/stable/
Project-URL: Bug Tracker, https://github.com/althonos/pyopal/issues
Project-URL: Changelog, https://github.com/althonos/pyopal/blob/master/CHANGELOG.md
Project-URL: Coverage, https://codecov.io/gh/althonos/pyopal/
Project-URL: Builds, https://github.com/althonos/pyopal/actions
Project-URL: PyPI, https://pypi.org/project/pyopal
Requires-Python: >=3.7
Requires-Dist: archspec~=0.2.0
Requires-Dist: scoring-matrices~=0.3.0
